pkl_gen_python.py
pkl/VERSION
pkl/__init__.py
pkl/binary_manager.py
pkl/evaluator_manager.py
pkl/evaluator_options.py
pkl/msgapi.py
pkl/parser.py
pkl/reader.py
pkl/server.py
pkl/utils.py
pkl_python-0.1.16.dist-info/LICENSE
pkl_python-0.1.16.dist-info/METADATA
pkl_python-0.1.16.dist-info/WHEEL
pkl_python-0.1.16.dist-info/entry_points.txt
pkl_python-0.1.16.dist-info/top_level.txt
pkl_python-0.1.16.dist-info/RECORD
